senscritique/__init__.py
senscritique/data_utils.py
senscritique/parse_utils.py
senscritique/process_collection.py
senscritique/process_critiques.py
senscritique/process_generic.py
senscritique/process_listes.py
senscritique/takeout.py
senscritique/utils.py
senscritique/tests/__init__.py
senscritique/tests/test_senscritique.py
senscritique-0.5.5.dist-info/LICENSE
senscritique-0.5.5.dist-info/METADATA
senscritique-0.5.5.dist-info/WHEEL
senscritique-0.5.5.dist-info/top_level.txt
senscritique-0.5.5.dist-info/RECORD
