Metadata-Version: 2.1
Name: senscritique
Version: 0.5.5
Summary: SensCritique Takeout on PyPI
Home-page: https://github.com/woctezuma/SensCritique-Takeout
Download-URL: https://github.com/woctezuma/SensCritique-Takeout/archive/0.5.5.tar.gz
Author: Wok
Author-email: wok@tuta.io
Keywords: senscritique,takeout,takeaway
Classifier: Development Status :: 4 - Beta
Classifier: Topic :: Games/Entertainment
Classifier: Programming Language :: Python :: 3
Classifier: License :: OSI Approved :: MIT License
Classifier: Operating System :: OS Independent
Classifier: Intended Audience :: End Users/Desktop
Classifier: Natural Language :: French
Requires-Python: >=3
License-File: LICENSE
Requires-Dist: beautifulsoup4
Requires-Dist: requests
Requires-Dist: lxml
